bpmnClient/__init__.py
bpmnClient/bpmn.py
bpmnClient/bpmn2.py
bpmnClient/client.py
bpmnClient/example.py
bpmnClient-1.0.8.dist-info/LICENSE
bpmnClient-1.0.8.dist-info/METADATA
bpmnClient-1.0.8.dist-info/WHEEL
bpmnClient-1.0.8.dist-info/top_level.txt
bpmnClient-1.0.8.dist-info/RECORD
