Metadata-Version: 2.1
Name: bpmnClient
Version: 1.0.8
Summary: bpmnServer python client
Author-email: ralph hanna <ralphhanna@hotmail.com>
Project-URL: Homepage, https://github.com/pypa/sampleproject
Project-URL: Issues, https://github.com/pypa/sampleproject/issues
Classifier: Programming Language :: Python :: 3
Classifier: License :: OSI Approved :: MIT License
Classifier: Operating System :: OS Independent
Requires-Python: >=3.8
License-File: LICENSE
